Metadata-Version: 2.1
Name: stimer
Version: 0.2.0
Summary: stimer stands for "simpletimer" and is a command line timer that features short "fuzzy" syntax and basic output.
Home-page: https://github.com/deynh/stimer
Author: Nicholas DeYarman
Author-email: ndeyarman@tutanota.com
License: UNKNOWN
Platform: UNKNOWN
Classifier: Programming Language :: Python :: 3
Classifier: License :: OSI Approved :: MIT License
Classifier: Operating System :: OS Independent
Requires-Python: >=3.7
